nanohubthemes/__init__.py
nanohubthemes/_version.py
nanohubthemes/jtplot.py
nanohubthemes/stylefx.py
nanohubthemes/defaults/custom-Copy1.css
nanohubthemes/defaults/custom-Copy1.js
nanohubthemes/defaults/custom.css
nanohubthemes/defaults/custom.js
nanohubthemes/fonts/monospace/anka-coder/anka-coder-italic.ttf
nanohubthemes/fonts/monospace/anka-coder/anka-coder.ttf
nanohubthemes/fonts/monospace/anka-coder/license.txt
nanohubthemes/fonts/monospace/anonymous-pro/anonymous-pro-italic.ttf
nanohubthemes/fonts/monospace/anonymous-pro/anonymous-pro.ttf
nanohubthemes/fonts/monospace/anonymous-pro/license.txt
nanohubthemes/fonts/monospace/aurulent/aurulent.otf
nanohubthemes/fonts/monospace/aurulent/license.txt
nanohubthemes/fonts/monospace/bitstream-vera/bitstream-vera-italic.woff
nanohubthemes/fonts/monospace/bitstream-vera/bitstream-vera.woff
nanohubthemes/fonts/monospace/bitstream-vera/license.txt
nanohubthemes/fonts/monospace/bpmono/bpmono-italic.woff
nanohubthemes/fonts/monospace/bpmono/bpmono.woff
nanohubthemes/fonts/monospace/bpmono/license.txt
nanohubthemes/fonts/monospace/code-new-roman/code-new-roman.otf
nanohubthemes/fonts/monospace/consolamono/consolamono.ttf
nanohubthemes/fonts/monospace/consolamono/license.txt
nanohubthemes/fonts/monospace/cousine/cousine-italic.ttf
nanohubthemes/fonts/monospace/cousine/cousine.ttf
nanohubthemes/fonts/monospace/cousine/license.txt
nanohubthemes/fonts/monospace/dejavu/dejavu-italic.ttf
nanohubthemes/fonts/monospace/dejavu/dejavu.ttf
nanohubthemes/fonts/monospace/dejavu/license.txt
nanohubthemes/fonts/monospace/droidmono/droid-sans-mono.woff
nanohubthemes/fonts/monospace/droidmono/license.txt
nanohubthemes/fonts/monospace/fira/fira.ttf
nanohubthemes/fonts/monospace/fira/license.txt
nanohubthemes/fonts/monospace/firacode/firacode.otf
nanohubthemes/fonts/monospace/generic/generic.otf
nanohubthemes/fonts/monospace/generic/license.txt
nanohubthemes/fonts/monospace/hack/hack-italic.ttf
nanohubthemes-0.0.6.dist-info/licenses/LICENSE.txt
nanohubthemes-0.0.6.dist-info/METADATA
nanohubthemes-0.0.6.dist-info/WHEEL
nanohubthemes-0.0.6.dist-info/entry_points.txt
nanohubthemes-0.0.6.dist-info/top_level.txt
nanohubthemes-0.0.6.dist-info/RECORD
